{"remainingRequest":"C:\\sepanuevo\\SEPA_APP_REACT\\SEPA_APP_REACT\\sepa\\node_modules\\thread-loader\\dist\\cjs.js??ref--4-2!C:\\sepanuevo\\SEPA_APP_REACT\\SEPA_APP_REACT\\sepa\\node_modules\\ts-loader\\index.js??ref--4-3!C:\\sepanuevo\\SEPA_APP_REACT\\SEPA_APP_REACT\\sepa\\node_modules\\eslint-loader\\index.js!C:\\sepanuevo\\SEPA_APP_REACT\\SEPA_APP_REACT\\sepa\\src\\main\\webapp\\app\\entities\\industry-type\\industry-type.tsx","dependencies":[{"path":"C:\\sepanuevo\\SEPA_APP_REACT\\SEPA_APP_REACT\\sepa\\src\\main\\webapp\\app\\entities\\industry-type\\industry-type.tsx","mtime":1584192247842},{"path":"C:\\sepanuevo\\SEPA_APP_REACT\\SEPA_APP_REACT\\sepa\\node_modules\\react-hot-loader\\webpack.js","mtime":499162500000},{"path":"C:\\sepanuevo\\SEPA_APP_REACT\\SEPA_APP_REACT\\sepa\\node_modules\\cache-loader\\dist\\cjs.js","mtime":499162500000},{"path":"C:\\sepanuevo\\SEPA_APP_REACT\\SEPA_APP_REACT\\sepa\\node_modules\\thread-loader\\dist\\cjs.js","mtime":499162500000},{"path":"C:\\sepanuevo\\SEPA_APP_REACT\\SEPA_APP_REACT\\sepa\\node_modules\\ts-loader\\index.js","mtime":1545640398000},{"path":"C:\\sepanuevo\\SEPA_APP_REACT\\SEPA_APP_REACT\\sepa\\node_modules\\eslint-loader\\index.js","mtime":499162500000}],"contextDependencies":[],"result":["import React from 'react';\r\nimport { connect } from 'react-redux';\r\nimport { Link } from 'react-router-dom';\r\nimport { Button, InputGroup, Col, Row, Table } from 'reactstrap';\r\nimport { AvForm, AvGroup, AvInput } from 'availity-reactstrap-validation';\r\nimport { Translate, translate, getSortState, JhiPagination, JhiItemCount } from 'react-jhipster';\r\nimport { FontAwesomeIcon } from '@fortawesome/react-fontawesome';\r\nimport { getSearchEntities, getEntities } from './industry-type.reducer';\r\nimport { ITEMS_PER_PAGE } from 'app/shared/util/pagination.constants';\r\nexport class IndustryType extends React.Component {\r\n    constructor() {\r\n        super(...arguments);\r\n        this.state = Object.assign({ search: '' }, getSortState(this.props.location, ITEMS_PER_PAGE));\r\n        this.search = () => {\r\n            if (this.state.search) {\r\n                this.setState({ activePage: 1 }, () => {\r\n                    const { activePage, itemsPerPage, sort, order, search } = this.state;\r\n                    this.props.getSearchEntities(search, activePage - 1, itemsPerPage, `${sort},${order}`);\r\n                });\r\n            }\r\n        };\r\n        this.clear = () => {\r\n            this.setState({ search: '', activePage: 1 }, () => {\r\n                this.props.getEntities();\r\n            });\r\n        };\r\n        this.handleSearch = event => this.setState({ search: event.target.value });\r\n        this.sort = prop => () => {\r\n            this.setState({\r\n                order: this.state.order === 'asc' ? 'desc' : 'asc',\r\n                sort: prop\r\n            }, () => this.sortEntities());\r\n        };\r\n        this.handlePagination = activePage => this.setState({ activePage }, () => this.sortEntities());\r\n        this.getEntities = () => {\r\n            const { activePage, itemsPerPage, sort, order, search } = this.state;\r\n            if (search) {\r\n                this.props.getSearchEntities(search, activePage - 1, itemsPerPage, `${sort},${order}`);\r\n            }\r\n            else {\r\n                this.props.getEntities(activePage - 1, itemsPerPage, `${sort},${order}`);\r\n            }\r\n        };\r\n    }\r\n    componentDidMount() {\r\n        this.getEntities();\r\n    }\r\n    sortEntities() {\r\n        this.getEntities();\r\n        this.props.history.push(`${this.props.location.pathname}?page=${this.state.activePage}&sort=${this.state.sort},${this.state.order}`);\r\n    }\r\n    render() {\r\n        const { industryTypeList, match, totalItems } = this.props;\r\n        return (React.createElement(\"div\", null,\r\n            React.createElement(\"h2\", { id: \"industry-type-heading\" },\r\n                React.createElement(Translate, { contentKey: \"sepaApp.industryType.home.title\" }, \"Industry Types\"),\r\n                React.createElement(Link, { to: `${match.url}/new`, className: \"btn btn-primary float-right jh-create-entity\", id: \"jh-create-entity\" },\r\n                    React.createElement(FontAwesomeIcon, { icon: \"plus\" }),\r\n                    \"\\u00A0\",\r\n                    React.createElement(Translate, { contentKey: \"sepaApp.industryType.home.createLabel\" }, \"Create a new Industry Type\"))),\r\n            React.createElement(Row, null,\r\n                React.createElement(Col, { sm: \"12\" },\r\n                    React.createElement(AvForm, { onSubmit: this.search },\r\n                        React.createElement(AvGroup, null,\r\n                            React.createElement(InputGroup, null,\r\n                                React.createElement(AvInput, { type: \"text\", name: \"search\", value: this.state.search, onChange: this.handleSearch, placeholder: translate('sepaApp.industryType.home.search') }),\r\n                                React.createElement(Button, { className: \"input-group-addon\" },\r\n                                    React.createElement(FontAwesomeIcon, { icon: \"search\" })),\r\n                                React.createElement(Button, { type: \"reset\", className: \"input-group-addon\", onClick: this.clear },\r\n                                    React.createElement(FontAwesomeIcon, { icon: \"trash\" }))))))),\r\n            React.createElement(\"div\", { className: \"table-responsive\" }, industryTypeList && industryTypeList.length > 0 ? (React.createElement(Table, { responsive: true, \"aria-describedby\": \"industry-type-heading\" },\r\n                React.createElement(\"thead\", null,\r\n                    React.createElement(\"tr\", null,\r\n                        React.createElement(\"th\", { className: \"hand\", onClick: this.sort('name') },\r\n                            React.createElement(Translate, { contentKey: \"sepaApp.industryType.name\" }, \"Name\"),\r\n                            \" \",\r\n                            React.createElement(FontAwesomeIcon, { icon: \"sort\" })),\r\n                        React.createElement(\"th\", { className: \"hand\", onClick: this.sort('ciiu') },\r\n                            React.createElement(Translate, { contentKey: \"sepaApp.industryType.ciiu\" }, \"Ciiu\"),\r\n                            \" \",\r\n                            React.createElement(FontAwesomeIcon, { icon: \"sort\" })),\r\n                        React.createElement(\"th\", null))),\r\n                React.createElement(\"tbody\", null, industryTypeList.map((industryType, i) => (React.createElement(\"tr\", { key: `entity-${i}` },\r\n                    React.createElement(\"td\", null,\r\n                        React.createElement(Button, { tag: Link, to: `${match.url}/${industryType.id}`, color: \"link\", size: \"sm\" }, industryType.name)),\r\n                    React.createElement(\"td\", null, industryType.ciiu),\r\n                    React.createElement(\"td\", { className: \"text-right\" },\r\n                        React.createElement(\"div\", { className: \"btn-group flex-btn-group-container\" },\r\n                            React.createElement(Button, { tag: Link, to: `${match.url}/${industryType.id}`, color: \"info\", size: \"sm\" },\r\n                                React.createElement(FontAwesomeIcon, { icon: \"eye\" }),\r\n                                ' ',\r\n                                React.createElement(\"span\", { className: \"d-none d-md-inline\" },\r\n                                    React.createElement(Translate, { contentKey: \"entity.action.view\" }, \"View\"))),\r\n                            React.createElement(Button, { tag: Link, to: `${match.url}/${industryType.id}/edit`, color: \"primary\", size: \"sm\" },\r\n                                React.createElement(FontAwesomeIcon, { icon: \"pencil-alt\" }),\r\n                                ' ',\r\n                                React.createElement(\"span\", { className: \"d-none d-md-inline\" },\r\n                                    React.createElement(Translate, { contentKey: \"entity.action.edit\" }, \"Edit\"))),\r\n                            React.createElement(Button, { tag: Link, to: `${match.url}/${industryType.id}/delete`, color: \"danger\", size: \"sm\" },\r\n                                React.createElement(FontAwesomeIcon, { icon: \"trash\" }),\r\n                                ' ',\r\n                                React.createElement(\"span\", { className: \"d-none d-md-inline\" },\r\n                                    React.createElement(Translate, { contentKey: \"entity.action.delete\" }, \"Delete\"))))))))))) : (React.createElement(\"div\", { className: \"alert alert-warning\" },\r\n                React.createElement(Translate, { contentKey: \"sepaApp.industryType.home.notFound\" }, \"No Industry Types found\")))),\r\n            React.createElement(\"div\", { className: industryTypeList && industryTypeList.length > 0 ? '' : 'd-none' },\r\n                React.createElement(Row, { className: \"justify-content-center\" },\r\n                    React.createElement(JhiItemCount, { page: this.state.activePage, total: totalItems, itemsPerPage: this.state.itemsPerPage, i18nEnabled: true })),\r\n                React.createElement(Row, { className: \"justify-content-center\" },\r\n                    React.createElement(JhiPagination, { activePage: this.state.activePage, onSelect: this.handlePagination, maxButtons: 5, itemsPerPage: this.state.itemsPerPage, totalItems: this.props.totalItems })))));\r\n    }\r\n}\r\nconst mapStateToProps = ({ industryType }) => ({\r\n    industryTypeList: industryType.entities,\r\n    totalItems: industryType.totalItems\r\n});\r\nconst mapDispatchToProps = {\r\n    getSearchEntities,\r\n    getEntities\r\n};\r\nexport default connect(mapStateToProps, mapDispatchToProps)(IndustryType);\r\n",{"version":3,"file":"C:\\sepanuevo\\SEPA_APP_REACT\\SEPA_APP_REACT\\sepa\\src\\main\\webapp\\app\\entities\\industry-type\\industry-type.tsx","sourceRoot":"","sources":["C:\\sepanuevo\\SEPA_APP_REACT\\SEPA_APP_REACT\\sepa\\node_modules\\eslint-loader\\index.js!C:\\sepanuevo\\SEPA_APP_REACT\\SEPA_APP_REACT\\sepa\\src\\main\\webapp\\app\\entities\\industry-type\\industry-type.tsx"],"names":[],"mappings":"AAAA,OAAO,KAAK,MAAM,OAAO,CAAC;AAC1B,OAAO,EAAE,OAAO,EAAE,MAAM,aAAa,CAAC;AACtC,OAAO,EAAE,IAAI,EAAuB,MAAM,kBAAkB,CAAC;AAC7D,OAAO,EAAE,MAAM,EAAE,UAAU,EAAE,GAAG,EAAE,GAAG,EAAE,KAAK,EAAE,MAAM,YAAY,CAAC;AACjE,OAAO,EAAE,MAAM,EAAE,OAAO,EAAE,OAAO,EAAE,MAAM,gCAAgC,CAAC;AAC1E,OAAO,EACL,SAAS,EACT,SAAS,EAIT,YAAY,EAEZ,aAAa,EACb,YAAY,EACb,MAAM,gBAAgB,CAAC;AACxB,OAAO,EAAE,eAAe,EAAE,MAAM,gCAAgC,CAAC;AAGjE,OAAO,EAAE,iBAAiB,EAAE,WAAW,EAAE,MAAM,yBAAyB,CAAC;AAGzE,OAAO,EAAE,cAAc,EAAE,MAAM,sCAAsC,CAAC;AAQtE,MAAM,OAAO,YAAa,SAAQ,KAAK,CAAC,SAAiD;IAAzF;;QACE,UAAK,mBACH,MAAM,EAAE,EAAE,IACP,YAAY,CAAC,IAAI,CAAC,KAAK,CAAC,QAAQ,EAAE,cAAc,CAAC,EACpD;QAMF,WAAM,GAAG,GAAG,EAAE;YACZ,IAAI,IAAI,CAAC,KAAK,CAAC,MAAM,EAAE;gBACrB,IAAI,CAAC,QAAQ,CAAC,EAAE,UAAU,EAAE,CAAC,EAAE,EAAE,GAAG,EAAE;oBACpC,MAAM,EAAE,UAAU,EAAE,YAAY,EAAE,IAAI,EAAE,KAAK,EAAE,MAAM,EAAE,GAAG,IAAI,CAAC,KAAK,CAAC;oBACrE,IAAI,CAAC,KAAK,CAAC,iBAAiB,CAAC,MAAM,EAAE,UAAU,GAAG,CAAC,EAAE,YAAY,EAAE,GAAG,IAAI,IAAI,KAAK,EAAE,CAAC,CAAC;gBACzF,CAAC,CAAC,CAAC;aACJ;QACH,CAAC,CAAC;QAEF,UAAK,GAAG,GAAG,EAAE;YACX,IAAI,CAAC,QAAQ,CAAC,EAAE,MAAM,EAAE,EAAE,EAAE,UAAU,EAAE,CAAC,EAAE,EAAE,GAAG,EAAE;gBAChD,IAAI,CAAC,KAAK,CAAC,WAAW,EAAE,CAAC;YAC3B,CAAC,CAAC,CAAC;QACL,CAAC,CAAC;QAEF,iBAAY,GAAG,KAAK,CAAC,EAAE,CAAC,IAAI,CAAC,QAAQ,CAAC,EAAE,MAAM,EAAE,KAAK,CAAC,MAAM,CAAC,KAAK,EAAE,CAAC,CAAC;QAEtE,SAAI,GAAG,IAAI,CAAC,EAAE,CAAC,GAAG,EAAE;YAClB,IAAI,CAAC,QAAQ,CACX;gBACE,KAAK,EAAE,IAAI,CAAC,KAAK,CAAC,KAAK,KAAK,KAAK,CAAC,CAAC,CAAC,MAAM,CAAC,CAAC,CAAC,KAAK;gBAClD,IAAI,EAAE,IAAI;aACX,EACD,GAAG,EAAE,CAAC,IAAI,CAAC,YAAY,EAAE,CAC1B,CAAC;QACJ,CAAC,CAAC;QAOF,qBAAgB,GAAG,UAAU,CAAC,EAAE,CAAC,IAAI,CAAC,QAAQ,CAAC,EAAE,UAAU,EAAE,EAAE,GAAG,EAAE,CAAC,IAAI,CAAC,YAAY,EAAE,CAAC,CAAC;QAE1F,gBAAW,GAAG,GAAG,EAAE;YACjB,MAAM,EAAE,UAAU,EAAE,YAAY,EAAE,IAAI,EAAE,KAAK,EAAE,MAAM,EAAE,GAAG,IAAI,CAAC,KAAK,CAAC;YACrE,IAAI,MAAM,EAAE;gBACV,IAAI,CAAC,KAAK,CAAC,iBAAiB,CAAC,MAAM,EAAE,UAAU,GAAG,CAAC,EAAE,YAAY,EAAE,GAAG,IAAI,IAAI,KAAK,EAAE,CAAC,CAAC;aACxF;iBAAM;gBACL,IAAI,CAAC,KAAK,CAAC,WAAW,CAAC,UAAU,GAAG,CAAC,EAAE,YAAY,EAAE,GAAG,IAAI,IAAI,KAAK,EAAE,CAAC,CAAC;aAC1E;QACH,CAAC,CAAC;IA6GJ,CAAC;IA1JC,iBAAiB;QACf,IAAI,CAAC,WAAW,EAAE,CAAC;IACrB,CAAC;IA6BD,YAAY;QACV,IAAI,CAAC,WAAW,EAAE,CAAC;QACnB,IAAI,CAAC,KAAK,CAAC,OAAO,CAAC,IAAI,CAAC,GAAG,IAAI,CAAC,KAAK,CAAC,QAAQ,CAAC,QAAQ,SAAS,IAAI,CAAC,KAAK,CAAC,UAAU,SAAS,IAAI,CAAC,KAAK,CAAC,IAAI,IAAI,IAAI,CAAC,KAAK,CAAC,KAAK,EAAE,CAAC,CAAC;IACvI,CAAC;IAaD,MAAM;QACJ,MAAM,EAAE,gBAAgB,EAAE,KAAK,EAAE,UAAU,EAAE,GAAG,IAAI,CAAC,KAAK,CAAC;QAC3D,OAAO,CACL;YACE,4BAAI,EAAE,EAAC,uBAAuB;gBAC5B,oBAAC,SAAS,IAAC,UAAU,EAAC,iCAAiC,qBAA2B;gBAClF,oBAAC,IAAI,IAAC,EAAE,EAAE,GAAG,KAAK,CAAC,GAAG,MAAM,EAAE,SAAS,EAAC,8CAA8C,EAAC,EAAE,EAAC,kBAAkB;oBAC1G,oBAAC,eAAe,IAAC,IAAI,EAAC,MAAM,GAAG;;oBAE/B,oBAAC,SAAS,IAAC,UAAU,EAAC,uCAAuC,iCAAuC,CAC/F,CACJ;YACL,oBAAC,GAAG;gBACF,oBAAC,GAAG,IAAC,EAAE,EAAC,IAAI;oBACV,oBAAC,MAAM,IAAC,QAAQ,EAAE,IAAI,CAAC,MAAM;wBAC3B,oBAAC,OAAO;4BACN,oBAAC,UAAU;gCACT,oBAAC,OAAO,IACN,IAAI,EAAC,MAAM,EACX,IAAI,EAAC,QAAQ,EACb,KAAK,EAAE,IAAI,CAAC,KAAK,CAAC,MAAM,EACxB,QAAQ,EAAE,IAAI,CAAC,YAAY,EAC3B,WAAW,EAAE,SAAS,CAAC,kCAAkC,CAAC,GAC1D;gCACF,oBAAC,MAAM,IAAC,SAAS,EAAC,mBAAmB;oCACnC,oBAAC,eAAe,IAAC,IAAI,EAAC,QAAQ,GAAG,CAC1B;gCACT,oBAAC,MAAM,IAAC,IAAI,EAAC,OAAO,EAAC,SAAS,EAAC,mBAAmB,EAAC,OAAO,EAAE,IAAI,CAAC,KAAK;oCACpE,oBAAC,eAAe,IAAC,IAAI,EAAC,OAAO,GAAG,CACzB,CACE,CACL,CACH,CACL,CACF;YACN,6BAAK,SAAS,EAAC,kBAAkB,IAC9B,gBAAgB,IAAI,gBAAgB,CAAC,MAAM,GAAG,CAAC,CAAC,CAAC,CAAC,CACjD,oBAAC,KAAK,IAAC,UAAU,4BAAkB,uBAAuB;gBACxD;oBACE;wBACE,4BAAI,SAAS,EAAC,MAAM,EAAC,OAAO,EAAE,IAAI,CAAC,IAAI,CAAC,MAAM,CAAC;4BAC7C,oBAAC,SAAS,IAAC,UAAU,EAAC,2BAA2B,WAAiB;;4BAAC,oBAAC,eAAe,IAAC,IAAI,EAAC,MAAM,GAAG,CAC/F;wBACL,4BAAI,SAAS,EAAC,MAAM,EAAC,OAAO,EAAE,IAAI,CAAC,IAAI,CAAC,MAAM,CAAC;4BAC7C,oBAAC,SAAS,IAAC,UAAU,EAAC,2BAA2B,WAAiB;;4BAAC,oBAAC,eAAe,IAAC,IAAI,EAAC,MAAM,GAAG,CAC/F;wBACL,+BAAM,CACH,CACC;gBACR,mCACG,gBAAgB,CAAC,GAAG,CAAC,CAAC,YAAY,EAAE,CAAC,EAAE,EAAE,CAAC,CACzC,4BAAI,GAAG,EAAE,UAAU,CAAC,EAAE;oBACpB;wBACE,oBAAC,MAAM,IAAC,GAAG,EAAE,IAAI,EAAE,EAAE,EAAE,GAAG,KAAK,CAAC,GAAG,IAAI,YAAY,CAAC,EAAE,EAAE,EAAE,KAAK,EAAC,MAAM,EAAC,IAAI,EAAC,IAAI,IAC7E,YAAY,CAAC,IAAI,CACX,CACN;oBACL,gCAAK,YAAY,CAAC,IAAI,CAAM;oBAC5B,4BAAI,SAAS,EAAC,YAAY;wBACxB,6BAAK,SAAS,EAAC,oCAAoC;4BACjD,oBAAC,MAAM,IAAC,GAAG,EAAE,IAAI,EAAE,EAAE,EAAE,GAAG,KAAK,CAAC,GAAG,IAAI,YAAY,CAAC,EAAE,EAAE,EAAE,KAAK,EAAC,MAAM,EAAC,IAAI,EAAC,IAAI;gCAC9E,oBAAC,eAAe,IAAC,IAAI,EAAC,KAAK,GAAG;gCAAC,GAAG;gCAClC,8BAAM,SAAS,EAAC,oBAAoB;oCAClC,oBAAC,SAAS,IAAC,UAAU,EAAC,oBAAoB,WAAiB,CACtD,CACA;4BACT,oBAAC,MAAM,IAAC,GAAG,EAAE,IAAI,EAAE,EAAE,EAAE,GAAG,KAAK,CAAC,GAAG,IAAI,YAAY,CAAC,EAAE,OAAO,EAAE,KAAK,EAAC,SAAS,EAAC,IAAI,EAAC,IAAI;gCACtF,oBAAC,eAAe,IAAC,IAAI,EAAC,YAAY,GAAG;gCAAC,GAAG;gCACzC,8BAAM,SAAS,EAAC,oBAAoB;oCAClC,oBAAC,SAAS,IAAC,UAAU,EAAC,oBAAoB,WAAiB,CACtD,CACA;4BACT,oBAAC,MAAM,IAAC,GAAG,EAAE,IAAI,EAAE,EAAE,EAAE,GAAG,KAAK,CAAC,GAAG,IAAI,YAAY,CAAC,EAAE,SAAS,EAAE,KAAK,EAAC,QAAQ,EAAC,IAAI,EAAC,IAAI;gCACvF,oBAAC,eAAe,IAAC,IAAI,EAAC,OAAO,GAAG;gCAAC,GAAG;gCACpC,8BAAM,SAAS,EAAC,oBAAoB;oCAClC,oBAAC,SAAS,IAAC,UAAU,EAAC,sBAAsB,aAAmB,CAC1D,CACA,CACL,CACH,CACF,CACN,CAAC,CACI,CACF,CACT,CAAC,CAAC,CAAC,CACF,6BAAK,SAAS,EAAC,qBAAqB;gBAClC,oBAAC,SAAS,IAAC,UAAU,EAAC,oCAAoC,8BAAoC,CAC1F,CACP,CACG;YACN,6BAAK,SAAS,EAAE,gBAAgB,IAAI,gBAAgB,CAAC,MAAM,GAAG,CAAC,CAAC,CAAC,CAAC,EAAE,CAAC,CAAC,CAAC,QAAQ;gBAC7E,oBAAC,GAAG,IAAC,SAAS,EAAC,wBAAwB;oBACrC,oBAAC,YAAY,IAAC,IAAI,EAAE,IAAI,CAAC,KAAK,CAAC,UAAU,EAAE,KAAK,EAAE,UAAU,EAAE,YAAY,EAAE,IAAI,CAAC,KAAK,CAAC,YAAY,EAAE,WAAW,SAAG,CAC/G;gBACN,oBAAC,GAAG,IAAC,SAAS,EAAC,wBAAwB;oBACrC,oBAAC,aAAa,IACZ,UAAU,EAAE,IAAI,CAAC,KAAK,CAAC,UAAU,EACjC,QAAQ,EAAE,IAAI,CAAC,gBAAgB,EAC/B,UAAU,EAAE,CAAC,EACb,YAAY,EAAE,IAAI,CAAC,KAAK,CAAC,YAAY,EACrC,UAAU,EAAE,IAAI,CAAC,KAAK,CAAC,UAAU,GACjC,CACE,CACF,CACF,CACP,CAAC;IACJ,CAAC;CACF;AAED,MAAM,eAAe,GAAG,CAAC,EAAE,YAAY,EAAc,EAAE,EAAE,CAAC,CAAC;IACzD,gBAAgB,EAAE,YAAY,CAAC,QAAQ;IACvC,UAAU,EAAE,YAAY,CAAC,UAAU;CACpC,CAAC,CAAC;AAEH,MAAM,kBAAkB,GAAG;IACzB,iBAAiB;IACjB,WAAW;CACZ,CAAC;AAKF,eAAe,OAAO,CACpB,eAAe,EACf,kBAAkB,CACnB,CAAC,YAAY,CAAC,CAAC","sourcesContent":["import React from 'react';\r\nimport { connect } from 'react-redux';\r\nimport { Link, RouteComponentProps } from 'react-router-dom';\r\nimport { Button, InputGroup, Col, Row, Table } from 'reactstrap';\r\nimport { AvForm, AvGroup, AvInput } from 'availity-reactstrap-validation';\r\nimport {\r\n  Translate,\r\n  translate,\r\n  ICrudSearchAction,\r\n  ICrudGetAllAction,\r\n  TextFormat,\r\n  getSortState,\r\n  IPaginationBaseState,\r\n  JhiPagination,\r\n  JhiItemCount\r\n} from 'react-jhipster';\r\nimport { FontAwesomeIcon } from '@fortawesome/react-fontawesome';\r\n\r\nimport { IRootState } from 'app/shared/reducers';\r\nimport { getSearchEntities, getEntities } from './industry-type.reducer';\r\nimport { IIndustryType } from 'app/shared/model/industry-type.model';\r\nimport { APP_DATE_FORMAT, APP_LOCAL_DATE_FORMAT } from 'app/config/constants';\r\nimport { ITEMS_PER_PAGE } from 'app/shared/util/pagination.constants';\r\n\r\nexport interface IIndustryTypeProps extends StateProps, DispatchProps, RouteComponentProps<{ url: string }> {}\r\n\r\nexport interface IIndustryTypeState extends IPaginationBaseState {\r\n  search: string;\r\n}\r\n\r\nexport class IndustryType extends React.Component<IIndustryTypeProps, IIndustryTypeState> {\r\n  state: IIndustryTypeState = {\r\n    search: '',\r\n    ...getSortState(this.props.location, ITEMS_PER_PAGE)\r\n  };\r\n\r\n  componentDidMount() {\r\n    this.getEntities();\r\n  }\r\n\r\n  search = () => {\r\n    if (this.state.search) {\r\n      this.setState({ activePage: 1 }, () => {\r\n        const { activePage, itemsPerPage, sort, order, search } = this.state;\r\n        this.props.getSearchEntities(search, activePage - 1, itemsPerPage, `${sort},${order}`);\r\n      });\r\n    }\r\n  };\r\n\r\n  clear = () => {\r\n    this.setState({ search: '', activePage: 1 }, () => {\r\n      this.props.getEntities();\r\n    });\r\n  };\r\n\r\n  handleSearch = event => this.setState({ search: event.target.value });\r\n\r\n  sort = prop => () => {\r\n    this.setState(\r\n      {\r\n        order: this.state.order === 'asc' ? 'desc' : 'asc',\r\n        sort: prop\r\n      },\r\n      () => this.sortEntities()\r\n    );\r\n  };\r\n\r\n  sortEntities() {\r\n    this.getEntities();\r\n    this.props.history.push(`${this.props.location.pathname}?page=${this.state.activePage}&sort=${this.state.sort},${this.state.order}`);\r\n  }\r\n\r\n  handlePagination = activePage => this.setState({ activePage }, () => this.sortEntities());\r\n\r\n  getEntities = () => {\r\n    const { activePage, itemsPerPage, sort, order, search } = this.state;\r\n    if (search) {\r\n      this.props.getSearchEntities(search, activePage - 1, itemsPerPage, `${sort},${order}`);\r\n    } else {\r\n      this.props.getEntities(activePage - 1, itemsPerPage, `${sort},${order}`);\r\n    }\r\n  };\r\n\r\n  render() {\r\n    const { industryTypeList, match, totalItems } = this.props;\r\n    return (\r\n      <div>\r\n        <h2 id=\"industry-type-heading\">\r\n          <Translate contentKey=\"sepaApp.industryType.home.title\">Industry Types</Translate>\r\n          <Link to={`${match.url}/new`} className=\"btn btn-primary float-right jh-create-entity\" id=\"jh-create-entity\">\r\n            <FontAwesomeIcon icon=\"plus\" />\r\n            &nbsp;\r\n            <Translate contentKey=\"sepaApp.industryType.home.createLabel\">Create a new Industry Type</Translate>\r\n          </Link>\r\n        </h2>\r\n        <Row>\r\n          <Col sm=\"12\">\r\n            <AvForm onSubmit={this.search}>\r\n              <AvGroup>\r\n                <InputGroup>\r\n                  <AvInput\r\n                    type=\"text\"\r\n                    name=\"search\"\r\n                    value={this.state.search}\r\n                    onChange={this.handleSearch}\r\n                    placeholder={translate('sepaApp.industryType.home.search')}\r\n                  />\r\n                  <Button className=\"input-group-addon\">\r\n                    <FontAwesomeIcon icon=\"search\" />\r\n                  </Button>\r\n                  <Button type=\"reset\" className=\"input-group-addon\" onClick={this.clear}>\r\n                    <FontAwesomeIcon icon=\"trash\" />\r\n                  </Button>\r\n                </InputGroup>\r\n              </AvGroup>\r\n            </AvForm>\r\n          </Col>\r\n        </Row>\r\n        <div className=\"table-responsive\">\r\n          {industryTypeList && industryTypeList.length > 0 ? (\r\n            <Table responsive aria-describedby=\"industry-type-heading\">\r\n              <thead>\r\n                <tr>\r\n                  <th className=\"hand\" onClick={this.sort('name')}>\r\n                    <Translate contentKey=\"sepaApp.industryType.name\">Name</Translate> <FontAwesomeIcon icon=\"sort\" />\r\n                  </th>\r\n                  <th className=\"hand\" onClick={this.sort('ciiu')}>\r\n                    <Translate contentKey=\"sepaApp.industryType.ciiu\">Ciiu</Translate> <FontAwesomeIcon icon=\"sort\" />\r\n                  </th>\r\n                  <th />\r\n                </tr>\r\n              </thead>\r\n              <tbody>\r\n                {industryTypeList.map((industryType, i) => (\r\n                  <tr key={`entity-${i}`}>\r\n                    <td>\r\n                      <Button tag={Link} to={`${match.url}/${industryType.id}`} color=\"link\" size=\"sm\">\r\n                        {industryType.name}\r\n                      </Button>\r\n                    </td>\r\n                    <td>{industryType.ciiu}</td>\r\n                    <td className=\"text-right\">\r\n                      <div className=\"btn-group flex-btn-group-container\">\r\n                        <Button tag={Link} to={`${match.url}/${industryType.id}`} color=\"info\" size=\"sm\">\r\n                          <FontAwesomeIcon icon=\"eye\" />{' '}\r\n                          <span className=\"d-none d-md-inline\">\r\n                            <Translate contentKey=\"entity.action.view\">View</Translate>\r\n                          </span>\r\n                        </Button>\r\n                        <Button tag={Link} to={`${match.url}/${industryType.id}/edit`} color=\"primary\" size=\"sm\">\r\n                          <FontAwesomeIcon icon=\"pencil-alt\" />{' '}\r\n                          <span className=\"d-none d-md-inline\">\r\n                            <Translate contentKey=\"entity.action.edit\">Edit</Translate>\r\n                          </span>\r\n                        </Button>\r\n                        <Button tag={Link} to={`${match.url}/${industryType.id}/delete`} color=\"danger\" size=\"sm\">\r\n                          <FontAwesomeIcon icon=\"trash\" />{' '}\r\n                          <span className=\"d-none d-md-inline\">\r\n                            <Translate contentKey=\"entity.action.delete\">Delete</Translate>\r\n                          </span>\r\n                        </Button>\r\n                      </div>\r\n                    </td>\r\n                  </tr>\r\n                ))}\r\n              </tbody>\r\n            </Table>\r\n          ) : (\r\n            <div className=\"alert alert-warning\">\r\n              <Translate contentKey=\"sepaApp.industryType.home.notFound\">No Industry Types found</Translate>\r\n            </div>\r\n          )}\r\n        </div>\r\n        <div className={industryTypeList && industryTypeList.length > 0 ? '' : 'd-none'}>\r\n          <Row className=\"justify-content-center\">\r\n            <JhiItemCount page={this.state.activePage} total={totalItems} itemsPerPage={this.state.itemsPerPage} i18nEnabled />\r\n          </Row>\r\n          <Row className=\"justify-content-center\">\r\n            <JhiPagination\r\n              activePage={this.state.activePage}\r\n              onSelect={this.handlePagination}\r\n              maxButtons={5}\r\n              itemsPerPage={this.state.itemsPerPage}\r\n              totalItems={this.props.totalItems}\r\n            />\r\n          </Row>\r\n        </div>\r\n      </div>\r\n    );\r\n  }\r\n}\r\n\r\nconst mapStateToProps = ({ industryType }: IRootState) => ({\r\n  industryTypeList: industryType.entities,\r\n  totalItems: industryType.totalItems\r\n});\r\n\r\nconst mapDispatchToProps = {\r\n  getSearchEntities,\r\n  getEntities\r\n};\r\n\r\ntype StateProps = ReturnType<typeof mapStateToProps>;\r\ntype DispatchProps = typeof mapDispatchToProps;\r\n\r\nexport default connect(\r\n  mapStateToProps,\r\n  mapDispatchToProps\r\n)(IndustryType);\r\n"]}]}